{
  "HOME": "/",
  "LOGIN": "/login",
  "SIGNUP": "/signup",
  "FORGOT_PASSWORD": "/forgot-password",
  "RESEND_PASSWORD": "/resend-password",
  "CHANGE_PASSWORD": "/reset-password",
  "CHANGE_PASSWORD_SUCCESS": "/reset-password-success",
  "PRIVACY": "/privacy",
  "ADMIN": "/admin",
  "ROLES": "/roles",
  "ROLE": "/role/:name",
  "USERS": "/users",
  "PERMISSIONS": "/permissions",
  "DASHBOARD": "/dashboard",
  "USER": "/user",
  "SITE": "/site",
  "SETTINGS": "/settings",
  "SALES": "/sales",
  "COURSES": "/courses",
  "COURSES_ENROLLED": "/courses/enrolled/:course",
  "NEW_COURSE": "/courses/new",
  "CURRICULUM": "/courses/:course/curriculum",
  "PRICING_PLAN": "/courses/:course/pricing",
  "LECTURE": "/courses/:course/lecture/:lecture",
  "NEW_LECTURE": "/courses/:course/curriculum/lecture/:lecture",
  "PROFILE": "/profile",
  "FILTER": "/filter/:role"
}
